{
  "gitSyncId": "6a451c9013289e1331252fc8_212808a4-ebfa-4731-9e34-64dde8b4b1d4",
  "id": "Leveling_AuthJS.isSessionValid",
  "pluginId": "js-plugin",
  "pluginType": "JS",
  "unpublishedAction": {
    "actionConfiguration": {
      "encodeParamsToggle": true,
      "jsArguments": [],
      "paginationType": "NONE",
      "timeoutInMillisecond": 10000
    },
    "collectionId": "Leveling_AuthJS",
    "confirmBeforeExecute": false,
    "datasource": {
      "isAutoGenerated": false,
      "name": "UNUSED_DATASOURCE",
      "pluginId": "js-plugin"
    },
    "dynamicBindingPathList": [
      {
        "key": "body"
      }
    ],
    "fullyQualifiedName": "AuthJS.isSessionValid",
    "name": "isSessionValid",
    "pageId": "Leveling",
    "runBehaviour": "MANUAL",
    "userSetOnLoad": false
  }
}