{
  "gitSyncId": "6a451c9013289e1331252fc8_c05e9e7e-8d0b-4b3f-a3c6-b783d8581ecf",
  "id": "Summary Page_HomeJS.ingestModel",
  "pluginId": "js-plugin",
  "pluginType": "JS",
  "unpublishedAction": {
    "actionConfiguration": {
      "encodeParamsToggle": true,
      "jsArguments": [
        {
          "name": "modelData"
        }
      ],
      "paginationType": "NONE",
      "timeoutInMillisecond": 10000
    },
    "collectionId": "Summary Page_HomeJS",
    "confirmBeforeExecute": false,
    "datasource": {
      "isAutoGenerated": false,
      "name": "UNUSED_DATASOURCE",
      "pluginId": "js-plugin"
    },
    "dynamicBindingPathList": [
      {
        "key": "body"
      }
    ],
    "fullyQualifiedName": "HomeJS.ingestModel",
    "name": "ingestModel",
    "pageId": "Summary Page",
    "runBehaviour": "MANUAL",
    "userSetOnLoad": false
  }
}