{
  "gitSyncId": "6a451c9013289e1331252fc8_c498a1f3-8fe6-42e6-9fa3-31a37450bdfa",
  "id": "Commerz (Cutting)_CommerzJS.onArticleSelect",
  "pluginId": "js-plugin",
  "pluginType": "JS",
  "unpublishedAction": {
    "actionConfiguration": {
      "encodeParamsToggle": true,
      "jsArguments": [],
      "paginationType": "NONE",
      "timeoutInMillisecond": 10000
    },
    "collectionId": "Commerz (Cutting)_CommerzJS",
    "confirmBeforeExecute": false,
    "datasource": {
      "isAutoGenerated": false,
      "name": "UNUSED_DATASOURCE",
      "pluginId": "js-plugin"
    },
    "dynamicBindingPathList": [
      {
        "key": "body"
      }
    ],
    "fullyQualifiedName": "CommerzJS.onArticleSelect",
    "name": "onArticleSelect",
    "pageId": "Commerz (Cutting)",
    "runBehaviour": "MANUAL",
    "userSetOnLoad": false
  }
}