{
  "gitSyncId": "6a451c9013289e1331252fc8_16ea07a4-1396-4c12-b95d-a449a38fe6d0",
  "id": "UT (Upper Treatment)_UTJS.onDeleteWIP",
  "pluginId": "js-plugin",
  "pluginType": "JS",
  "unpublishedAction": {
    "actionConfiguration": {
      "encodeParamsToggle": true,
      "jsArguments": [
        {
          "name": "wipId"
        }
      ],
      "paginationType": "NONE",
      "timeoutInMillisecond": 10000
    },
    "collectionId": "UT (Upper Treatment)_UTJS",
    "confirmBeforeExecute": false,
    "datasource": {
      "isAutoGenerated": false,
      "name": "UNUSED_DATASOURCE",
      "pluginId": "js-plugin"
    },
    "dynamicBindingPathList": [
      {
        "key": "body"
      }
    ],
    "fullyQualifiedName": "UTJS.onDeleteWIP",
    "name": "onDeleteWIP",
    "pageId": "UT (Upper Treatment)",
    "runBehaviour": "MANUAL",
    "userSetOnLoad": false
  }
}