{
  "gitSyncId": "6a451c9013289e1331252fc8_ebbfafc9-eaa1-4623-8b3a-0c4c45a5b51c",
  "id": "Leveling_ZsfJS.fetchZfgDataGen",
  "pluginId": "js-plugin",
  "pluginType": "JS",
  "unpublishedAction": {
    "actionConfiguration": {
      "encodeParamsToggle": true,
      "jsArguments": [
        {
          "name": "meta"
        }
      ],
      "paginationType": "NONE",
      "timeoutInMillisecond": 10000
    },
    "collectionId": "Leveling_ZsfJS",
    "confirmBeforeExecute": false,
    "datasource": {
      "isAutoGenerated": false,
      "name": "UNUSED_DATASOURCE",
      "pluginId": "js-plugin"
    },
    "dynamicBindingPathList": [
      {
        "key": "body"
      }
    ],
    "fullyQualifiedName": "ZsfJS.fetchZfgDataGen",
    "name": "fetchZfgDataGen",
    "pageId": "Leveling",
    "runBehaviour": "MANUAL",
    "userSetOnLoad": false
  }
}